[
  {
    "notificationItems": [
      {
        "eventType": "USER_DATA_USAGE_MEASURES",
        "timeStamp": "2019-03-16T01:27:14.994200Z",
        "ueIpv4Addr": "10.145.167.113",
        "startTime": "2019-03-16T01:27:12.079900Z",
        "userDataUsageMeasurements": [
          {
            "volumeMeasurement": {
              "totalVolume": 388662,
              "ulVolume": 40123,
              "dlVolume": 348539,
              "totalNbOfPackets": 671,
              "ulNbOfPackets": 316,
              "dlNbOfPackets": 355
            },
            "throughputMeasurement": {
              "ulThroughput": "110141 bps",
              "dlThroughput": "956769 bps",
              "ulPacketThroughput": "108.43 pps",
              "dlPacketThroughput": "121.81 pps"
            }
          }
        ]
      }
    ],
    "correlationId": "corr-e818758a0331",
    "appLabel": "instagram_IgSearchBrowse",
    "duration": 2.914
  },
  {
    "notificationItems": [
      {
        "eventType": "USER_DATA_USAGE_MEASURES",
        "timeStamp": "2019-03-16T01:27:19.861400Z",
        "ueIpv4Addr": "10.145.167.113",
        "startTime": "2019-03-16T01:27:15.007400Z",
        "userDataUsageMeasurements": [
          {
            "volumeMeasurement": {
              "totalVolume": 1910259,
              "ulVolume": 78088,
              "dlVolume": 1832171,
              "totalNbOfPackets": 2229,
              "ulNbOfPackets": 728,
              "dlNbOfPackets": 1501
            },
            "throughputMeasurement": {
              "ulThroughput": "128699 bps",
              "dlThroughput": "3019647 bps",
              "ulPacketThroughput": "149.98 pps",
              "dlPacketThroughput": "309.23 pps"
            }
          }
        ]
      }
    ],
    "correlationId": "corr-20b485dd3763",
    "appLabel": "instagram_IgSearchBrowse",
    "duration": 4.854
  },
  {
    "notificationItems": [
      {
        "eventType": "USER_DATA_USAGE_MEASURES",
        "timeStamp": "2019-03-16T01:27:24.911400Z",
        "ueIpv4Addr": "10.145.167.113",
        "startTime": "2019-03-16T01:27:23.337100Z",
        "userDataUsageMeasurements": [
          {
            "volumeMeasurement": {
              "totalVolume": 118916,
              "ulVolume": 13462,
              "dlVolume": 105454,
              "totalNbOfPackets": 186,
              "ulNbOfPackets": 74,
              "dlNbOfPackets": 112
            },
            "throughputMeasurement": {
              "ulThroughput": "68409 bps",
              "dlThroughput": "535878 bps",
              "ulPacketThroughput": "47.01 pps",
              "dlPacketThroughput": "71.14 pps"
            }
          }
        ]
      }
    ],
    "correlationId": "corr-f1d6be0b0df8",
    "appLabel": "instagram_IgSearchBrowse",
    "duration": 1.574
  },
  {
    "notificationItems": [
      {
        "eventType": "USER_DATA_USAGE_MEASURES",
        "timeStamp": "2019-03-16T01:27:29.751800Z",
        "ueIpv4Addr": "10.145.167.113",
        "startTime": "2019-03-16T01:27:25.009300Z",
        "userDataUsageMeasurements": [
          {
            "volumeMeasurement": {
              "totalVolume": 621847,
              "ulVolume": 38596,
              "dlVolume": 583251,
              "totalNbOfPackets": 782,
              "ulNbOfPackets": 298,
              "dlNbOfPackets": 484
            },
            "throughputMeasurement": {
              "ulThroughput": "65107 bps",
              "dlThroughput": "983871 bps",
              "ulPacketThroughput": "62.84 pps",
              "dlPacketThroughput": "102.06 pps"
            }
          }
        ]
      }
    ],
    "correlationId": "corr-430baab88ade",
    "appLabel": "instagram_IgSearchBrowse",
    "duration": 4.743
  },
  {
    "notificationItems": [
      {
        "eventType": "USER_DATA_USAGE_MEASURES",
        "timeStamp": "2019-03-16T01:27:31.389400Z",
        "ueIpv4Addr": "10.145.167.113",
        "startTime": "2019-03-16T01:27:30.506000Z",
        "userDataUsageMeasurements": [
          {
            "volumeMeasurement": {
              "totalVolume": 130531,
              "ulVolume": 1838,
              "dlVolume": 128693,
              "totalNbOfPackets": 118,
              "ulNbOfPackets": 14,
              "dlNbOfPackets": 104
            },
            "throughputMeasurement": {
              "ulThroughput": "16645 bps",
              "dlThroughput": "1165434 bps",
              "ulPacketThroughput": "15.85 pps",
              "dlPacketThroughput": "117.73 pps"
            }
          }
        ]
      }
    ],
    "correlationId": "corr-8329d677a9a8",
    "appLabel": "instagram_IgSearchBrowse",
    "duration": 0.883
  },
  {
    "notificationItems": [
      {
        "eventType": "USER_DATA_USAGE_MEASURES",
        "timeStamp": "2019-03-16T01:27:39.978000Z",
        "ueIpv4Addr": "10.145.167.113",
        "startTime": "2019-03-16T01:27:37.442600Z",
        "userDataUsageMeasurements": [
          {
            "volumeMeasurement": {
              "totalVolume": 200561,
              "ulVolume": 11991,
              "dlVolume": 188570,
              "totalNbOfPackets": 247,
              "ulNbOfPackets": 84,
              "dlNbOfPackets": 163
            },
            "throughputMeasurement": {
              "ulThroughput": "37835 bps",
              "dlThroughput": "594999 bps",
              "ulPacketThroughput": "33.13 pps",
              "dlPacketThroughput": "64.29 pps"
            }
          }
        ]
      }
    ],
    "correlationId": "corr-3647dae18c34",
    "appLabel": "instagram_IgSearchBrowse",
    "duration": 2.535
  },
  {
    "notificationItems": [
      {
        "eventType": "USER_DATA_USAGE_MEASURES",
        "timeStamp": "2019-03-16T01:27:40.101100Z",
        "ueIpv4Addr": "10.145.167.113",
        "startTime": "2019-03-16T01:27:40.000800Z",
        "userDataUsageMeasurements": [
          {
            "volumeMeasurement": {
              "totalVolume": 144351,
              "ulVolume": 2972,
              "dlVolume": 141379,
              "totalNbOfPackets": 143,
              "ulNbOfPackets": 30,
              "dlNbOfPackets": 113
            },
            "throughputMeasurement": {
              "ulThroughput": "237049 bps",
              "dlThroughput": "11276482 bps",
              "ulPacketThroughput": "299.10 pps",
              "dlPacketThroughput": "1126.62 pps"
            }
          }
        ]
      }
    ],
    "correlationId": "corr-fa6c40245952",
    "appLabel": "instagram_IgSearchBrowse",
    "duration": 0.1
  },
  {
    "notificationItems": [
      {
        "eventType": "USER_DATA_USAGE_MEASURES",
        "timeStamp": "2019-03-16T01:27:48.716200Z",
        "ueIpv4Addr": "10.145.167.113",
        "startTime": "2019-03-16T01:27:46.031400Z",
        "userDataUsageMeasurements": [
          {
            "volumeMeasurement": {
              "totalVolume": 322672,
              "ulVolume": 17321,
              "dlVolume": 305351,
              "totalNbOfPackets": 407,
              "ulNbOfPackets": 152,
              "dlNbOfPackets": 255
            },
            "throughputMeasurement": {
              "ulThroughput": "51612 bps",
              "dlThroughput": "909866 bps",
              "ulPacketThroughput": "56.62 pps",
              "dlPacketThroughput": "94.98 pps"
            }
          }
        ]
      }
    ],
    "correlationId": "corr-2f25faf63149",
    "appLabel": "instagram_IgSearchBrowse",
    "duration": 2.685
  },
  {
    "notificationItems": [
      {
        "eventType": "USER_DATA_USAGE_MEASURES",
        "timeStamp": "2019-03-16T01:27:54.999800Z",
        "ueIpv4Addr": "10.145.167.113",
        "startTime": "2019-03-16T01:27:54.626200Z",
        "userDataUsageMeasurements": [
          {
            "volumeMeasurement": {
              "totalVolume": 1790,
              "ulVolume": 381,
              "dlVolume": 1409,
              "totalNbOfPackets": 5,
              "ulNbOfPackets": 3,
              "dlNbOfPackets": 2
            },
            "throughputMeasurement": {
              "ulThroughput": "8158 bps",
              "dlThroughput": "30171 bps",
              "ulPacketThroughput": "8.03 pps",
              "dlPacketThroughput": "5.35 pps"
            }
          }
        ]
      }
    ],
    "correlationId": "corr-4792be24bdb5",
    "appLabel": "instagram_IgSearchBrowse",
    "duration": 0.374
  },
  {
    "notificationItems": [
      {
        "eventType": "USER_DATA_USAGE_MEASURES",
        "timeStamp": "2019-03-16T01:27:57.458400Z",
        "ueIpv4Addr": "10.145.167.113",
        "startTime": "2019-03-16T01:27:55.001300Z",
        "userDataUsageMeasurements": [
          {
            "volumeMeasurement": {
              "totalVolume": 454833,
              "ulVolume": 14773,
              "dlVolume": 440060,
              "totalNbOfPackets": 476,
              "ulNbOfPackets": 113,
              "dlNbOfPackets": 363
            },
            "throughputMeasurement": {
              "ulThroughput": "48099 bps",
              "dlThroughput": "1432779 bps",
              "ulPacketThroughput": "45.99 pps",
              "dlPacketThroughput": "147.74 pps"
            }
          }
        ]
      }
    ],
    "correlationId": "corr-6855425f218d",
    "appLabel": "instagram_IgSearchBrowse",
    "duration": 2.457
  },
  {
    "notificationItems": [
      {
        "eventType": "USER_DATA_USAGE_MEASURES",
        "timeStamp": "2019-03-16T01:28:04.308000Z",
        "ueIpv4Addr": "10.145.167.113",
        "startTime": "2019-03-16T01:28:00.049000Z",
        "userDataUsageMeasurements": [
          {
            "volumeMeasurement": {
              "totalVolume": 208475,
              "ulVolume": 11170,
              "dlVolume": 197305,
              "totalNbOfPackets": 250,
              "ulNbOfPackets": 78,
              "dlNbOfPackets": 172
            },
            "throughputMeasurement": {
              "ulThroughput": "20981 bps",
              "dlThroughput": "370613 bps",
              "ulPacketThroughput": "18.31 pps",
              "dlPacketThroughput": "40.39 pps"
            }
          }
        ]
      }
    ],
    "correlationId": "corr-40d2f733c347",
    "appLabel": "instagram_IgSearchBrowse",
    "duration": 4.259
  },
  {
    "notificationItems": [
      {
        "eventType": "USER_DATA_USAGE_MEASURES",
        "timeStamp": "2019-03-16T01:28:06.217300Z",
        "ueIpv4Addr": "10.145.167.113",
        "startTime": "2019-03-16T01:28:05.027900Z",
        "userDataUsageMeasurements": [
          {
            "volumeMeasurement": {
              "totalVolume": 349312,
              "ulVolume": 4751,
              "dlVolume": 344561,
              "totalNbOfPackets": 323,
              "ulNbOfPackets": 50,
              "dlNbOfPackets": 273
            },
            "throughputMeasurement": {
              "ulThroughput": "31956 bps",
              "dlThroughput": "2317545 bps",
              "ulPacketThroughput": "42.04 pps",
              "dlPacketThroughput": "229.53 pps"
            }
          }
        ]
      }
    ],
    "correlationId": "corr-fcd360fbdbb3",
    "appLabel": "instagram_IgSearchBrowse",
    "duration": 1.189
  },
  {
    "notificationItems": [
      {
        "eventType": "USER_DATA_USAGE_MEASURES",
        "timeStamp": "2019-03-16T03:49:44.999100Z",
        "ueIpv4Addr": "10.145.43.25",
        "startTime": "2019-03-16T03:49:42.368000Z",
        "userDataUsageMeasurements": [
          {
            "volumeMeasurement": {
              "totalVolume": 156744,
              "ulVolume": 73470,
              "dlVolume": 83274,
              "totalNbOfPackets": 330,
              "ulNbOfPackets": 175,
              "dlNbOfPackets": 155
            },
            "throughputMeasurement": {
              "ulThroughput": "223389 bps",
              "dlThroughput": "253199 bps",
              "ulPacketThroughput": "66.51 pps",
              "dlPacketThroughput": "58.91 pps"
            }
          }
        ]
      }
    ],
    "correlationId": "corr-d5453265b29c",
    "appLabel": "instagram_IgSearchBrowse",
    "duration": 2.631
  },
  {
    "notificationItems": [
      {
        "eventType": "USER_DATA_USAGE_MEASURES",
        "timeStamp": "2019-03-16T03:49:49.127900Z",
        "ueIpv4Addr": "10.145.43.25",
        "startTime": "2019-03-16T03:49:45.003200Z",
        "userDataUsageMeasurements": [
          {
            "volumeMeasurement": {
              "totalVolume": 988240,
              "ulVolume": 296864,
              "dlVolume": 691376,
              "totalNbOfPackets": 1465,
              "ulNbOfPackets": 766,
              "dlNbOfPackets": 699
            },
            "throughputMeasurement": {
              "ulThroughput": "575778 bps",
              "dlThroughput": "1340948 bps",
              "ulPacketThroughput": "185.71 pps",
              "dlPacketThroughput": "169.47 pps"
            }
          }
        ]
      }
    ],
    "correlationId": "corr-0268a6f78d6d",
    "appLabel": "instagram_IgSearchBrowse",
    "duration": 4.125
  },
  {
    "notificationItems": [
      {
        "eventType": "USER_DATA_USAGE_MEASURES",
        "timeStamp": "2019-03-16T03:49:54.997100Z",
        "ueIpv4Addr": "10.145.43.25",
        "startTime": "2019-03-16T03:49:50.018500Z",
        "userDataUsageMeasurements": [
          {
            "volumeMeasurement": {
              "totalVolume": 76342,
              "ulVolume": 27673,
              "dlVolume": 48669,
              "totalNbOfPackets": 168,
              "ulNbOfPackets": 87,
              "dlNbOfPackets": 81
            },
            "throughputMeasurement": {
              "ulThroughput": "44467 bps",
              "dlThroughput": "78205 bps",
              "ulPacketThroughput": "17.47 pps",
              "dlPacketThroughput": "16.27 pps"
            }
          }
        ]
      }
    ],
    "correlationId": "corr-9c14a4beddd5",
    "appLabel": "instagram_IgSearchBrowse",
    "duration": 4.979
  },
  {
    "notificationItems": [
      {
        "eventType": "USER_DATA_USAGE_MEASURES",
        "timeStamp": "2019-03-16T03:49:59.710300Z",
        "ueIpv4Addr": "10.145.43.25",
        "startTime": "2019-03-16T03:49:55Z",
        "userDataUsageMeasurements": [
          {
            "volumeMeasurement": {
              "totalVolume": 114598,
              "ulVolume": 10414,
              "dlVolume": 104184,
              "totalNbOfPackets": 196,
              "ulNbOfPackets": 100,
              "dlNbOfPackets": 96
            },
            "throughputMeasurement": {
              "ulThroughput": "17687 bps",
              "dlThroughput": "176947 bps",
              "ulPacketThroughput": "21.23 pps",
              "dlPacketThroughput": "20.38 pps"
            }
          }
        ]
      }
    ],
    "correlationId": "corr-6320c4f4b8bf",
    "appLabel": "instagram_IgSearchBrowse",
    "duration": 4.71
  },
  {
    "notificationItems": [
      {
        "eventType": "USER_DATA_USAGE_MEASURES",
        "timeStamp": "2019-03-16T03:50:01.779000Z",
        "ueIpv4Addr": "10.145.43.25",
        "startTime": "2019-03-16T03:50:00.708600Z",
        "userDataUsageMeasurements": [
          {
            "volumeMeasurement": {
              "totalVolume": 137857,
              "ulVolume": 8162,
              "dlVolume": 129695,
              "totalNbOfPackets": 211,
              "ulNbOfPackets": 107,
              "dlNbOfPackets": 104
            },
            "throughputMeasurement": {
              "ulThroughput": "61001 bps",
              "dlThroughput": "969320 bps",
              "ulPacketThroughput": "99.96 pps",
              "dlPacketThroughput": "97.16 pps"
            }
          }
        ]
      }
    ],
    "correlationId": "corr-2d08e8c205e7",
    "appLabel": "instagram_IgSearchBrowse",
    "duration": 1.07
  },
  {
    "notificationItems": [
      {
        "eventType": "USER_DATA_USAGE_MEASURES",
        "timeStamp": "2019-03-16T03:50:09.717300Z",
        "ueIpv4Addr": "10.145.43.25",
        "startTime": "2019-03-16T03:50:07.893900Z",
        "userDataUsageMeasurements": [
          {
            "volumeMeasurement": {
              "totalVolume": 80063,
              "ulVolume": 7004,
              "dlVolume": 73059,
              "totalNbOfPackets": 130,
              "ulNbOfPackets": 68,
              "dlNbOfPackets": 62
            },
            "throughputMeasurement": {
              "ulThroughput": "30729 bps",
              "dlThroughput": "320540 bps",
              "ulPacketThroughput": "37.29 pps",
              "dlPacketThroughput": "34.00 pps"
            }
          }
        ]
      }
    ],
    "correlationId": "corr-9d2fdff3acc1",
    "appLabel": "instagram_IgSearchBrowse",
    "duration": 1.823
  },
  {
    "notificationItems": [
      {
        "eventType": "USER_DATA_USAGE_MEASURES",
        "timeStamp": "2019-03-16T03:50:10.809500Z",
        "ueIpv4Addr": "10.145.43.25",
        "startTime": "2019-03-16T03:50:10.536700Z",
        "userDataUsageMeasurements": [
          {
            "volumeMeasurement": {
              "totalVolume": 148748,
              "ulVolume": 8789,
              "dlVolume": 139959,
              "totalNbOfPackets": 223,
              "ulNbOfPackets": 113,
              "dlNbOfPackets": 110
            },
            "throughputMeasurement": {
              "ulThroughput": "257742 bps",
              "dlThroughput": "4104370 bps",
              "ulPacketThroughput": "414.22 pps",
              "dlPacketThroughput": "403.23 pps"
            }
          }
        ]
      }
    ],
    "correlationId": "corr-32f5d0a4c126",
    "appLabel": "instagram_IgSearchBrowse",
    "duration": 0.273
  },
  {
    "notificationItems": [
      {
        "eventType": "USER_DATA_USAGE_MEASURES",
        "timeStamp": "2019-03-16T03:50:19.454300Z",
        "ueIpv4Addr": "10.145.43.25",
        "startTime": "2019-03-16T03:50:16.742500Z",
        "userDataUsageMeasurements": [
          {
            "volumeMeasurement": {
              "totalVolume": 167243,
              "ulVolume": 11785,
              "dlVolume": 155458,
              "totalNbOfPackets": 261,
              "ulNbOfPackets": 134,
              "dlNbOfPackets": 127
            },
            "throughputMeasurement": {
              "ulThroughput": "34767 bps",
              "dlThroughput": "458612 bps",
              "ulPacketThroughput": "49.41 pps",
              "dlPacketThroughput": "46.83 pps"
            }
          }
        ]
      }
    ],
    "correlationId": "corr-2a155154e75f",
    "appLabel": "instagram_IgSearchBrowse",
    "duration": 2.712
  },
  {
    "notificationItems": [
      {
        "eventType": "USER_DATA_USAGE_MEASURES",
        "timeStamp": "2019-03-16T03:50:24.647200Z",
        "ueIpv4Addr": "10.145.43.25",
        "startTime": "2019-03-16T03:50:24.116200Z",
        "userDataUsageMeasurements": [
          {
            "volumeMeasurement": {
              "totalVolume": 5358,
              "ulVolume": 1425,
              "dlVolume": 3933,
              "totalNbOfPackets": 10,
              "ulNbOfPackets": 5,
              "dlNbOfPackets": 5
            },
            "throughputMeasurement": {
              "ulThroughput": "21469 bps",
              "dlThroughput": "59254 bps",
              "ulPacketThroughput": "9.42 pps",
              "dlPacketThroughput": "9.42 pps"
            }
          }
        ]
      }
    ],
    "correlationId": "corr-d826a08ebf47",
    "appLabel": "instagram_IgSearchBrowse",
    "duration": 0.531
  },
  {
    "notificationItems": [
      {
        "eventType": "USER_DATA_USAGE_MEASURES",
        "timeStamp": "2019-03-16T03:50:28.118100Z",
        "ueIpv4Addr": "10.145.43.25",
        "startTime": "2019-03-16T03:50:25.161000Z",
        "userDataUsageMeasurements": [
          {
            "volumeMeasurement": {
              "totalVolume": 286005,
              "ulVolume": 14248,
              "dlVolume": 271757,
              "totalNbOfPackets": 398,
              "ulNbOfPackets": 178,
              "dlNbOfPackets": 220
            },
            "throughputMeasurement": {
              "ulThroughput": "38546 bps",
              "dlThroughput": "735199 bps",
              "ulPacketThroughput": "60.19 pps",
              "dlPacketThroughput": "74.40 pps"
            }
          }
        ]
      }
    ],
    "correlationId": "corr-73cb1a7b7a95",
    "appLabel": "instagram_IgSearchBrowse",
    "duration": 2.957
  },
  {
    "notificationItems": [
      {
        "eventType": "USER_DATA_USAGE_MEASURES",
        "timeStamp": "2019-03-16T03:50:34.551200Z",
        "ueIpv4Addr": "10.145.43.25",
        "startTime": "2019-03-16T03:50:34.104600Z",
        "userDataUsageMeasurements": [
          {
            "volumeMeasurement": {
              "totalVolume": 58916,
              "ulVolume": 4275,
              "dlVolume": 54641,
              "totalNbOfPackets": 85,
              "ulNbOfPackets": 39,
              "dlNbOfPackets": 46
            },
            "throughputMeasurement": {
              "ulThroughput": "76579 bps",
              "dlThroughput": "978791 bps",
              "ulPacketThroughput": "87.33 pps",
              "dlPacketThroughput": "103.00 pps"
            }
          }
        ]
      }
    ],
    "correlationId": "corr-a41e9252feaa",
    "appLabel": "instagram_IgSearchBrowse",
    "duration": 0.447
  },
  {
    "notificationItems": [
      {
        "eventType": "USER_DATA_USAGE_MEASURES",
        "timeStamp": "2019-03-16T03:50:37.098700Z",
        "ueIpv4Addr": "10.145.43.25",
        "startTime": "2019-03-16T03:50:35.538700Z",
        "userDataUsageMeasurements": [
          {
            "volumeMeasurement": {
              "totalVolume": 354969,
              "ulVolume": 10599,
              "dlVolume": 344370,
              "totalNbOfPackets": 406,
              "ulNbOfPackets": 136,
              "dlNbOfPackets": 270
            },
            "throughputMeasurement": {
              "ulThroughput": "54354 bps",
              "dlThroughput": "1766000 bps",
              "ulPacketThroughput": "87.18 pps",
              "dlPacketThroughput": "173.08 pps"
            }
          }
        ]
      }
    ],
    "correlationId": "corr-eace95902221",
    "appLabel": "instagram_IgSearchBrowse",
    "duration": 1.56
  },
  {
    "notificationItems": [
      {
        "eventType": "USER_DATA_USAGE_MEASURES",
        "timeStamp": "2019-03-16T04:02:09.925400Z",
        "ueIpv4Addr": "10.145.167.113",
        "startTime": "2019-03-16T04:02:08.069700Z",
        "userDataUsageMeasurements": [
          {
            "volumeMeasurement": {
              "totalVolume": 144278,
              "ulVolume": 68642,
              "dlVolume": 75636,
              "totalNbOfPackets": 292,
              "ulNbOfPackets": 156,
              "dlNbOfPackets": 136
            },
            "throughputMeasurement": {
              "ulThroughput": "295919 bps",
              "dlThroughput": "326070 bps",
              "ulPacketThroughput": "84.07 pps",
              "dlPacketThroughput": "73.29 pps"
            }
          }
        ]
      }
    ],
    "correlationId": "corr-a52571ffcc5c",
    "appLabel": "instagram_IgSearchBrowse",
    "duration": 1.856
  },
  {
    "notificationItems": [
      {
        "eventType": "USER_DATA_USAGE_MEASURES",
        "timeStamp": "2019-03-16T04:02:14.930700Z",
        "ueIpv4Addr": "10.145.167.113",
        "startTime": "2019-03-16T04:02:10.052200Z",
        "userDataUsageMeasurements": [
          {
            "volumeMeasurement": {
              "totalVolume": 2523294,
              "ulVolume": 102872,
              "dlVolume": 2420422,
              "totalNbOfPackets": 2967,
              "ulNbOfPackets": 1001,
              "dlNbOfPackets": 1966
            },
            "throughputMeasurement": {
              "ulThroughput": "168694 bps",
              "dlThroughput": "3969125 bps",
              "ulPacketThroughput": "205.19 pps",
              "dlPacketThroughput": "402.99 pps"
            }
          }
        ]
      }
    ],
    "correlationId": "corr-4de761b3c54a",
    "appLabel": "instagram_IgSearchBrowse",
    "duration": 4.878
  },
  {
    "notificationItems": [
      {
        "eventType": "USER_DATA_USAGE_MEASURES",
        "timeStamp": "2019-03-16T04:02:19.987200Z",
        "ueIpv4Addr": "10.145.167.113",
        "startTime": "2019-03-16T04:02:19.541600Z",
        "userDataUsageMeasurements": [
          {
            "volumeMeasurement": {
              "totalVolume": 35830,
              "ulVolume": 4209,
              "dlVolume": 31621,
              "totalNbOfPackets": 72,
              "ulNbOfPackets": 35,
              "dlNbOfPackets": 37
            },
            "throughputMeasurement": {
              "ulThroughput": "75566 bps",
              "dlThroughput": "567702 bps",
              "ulPacketThroughput": "78.55 pps",
              "dlPacketThroughput": "83.03 pps"
            }
          }
        ]
      }
    ],
    "correlationId": "corr-1f57d9798c44",
    "appLabel": "instagram_IgSearchBrowse",
    "duration": 0.446
  },
  {
    "notificationItems": [
      {
        "eventType": "USER_DATA_USAGE_MEASURES",
        "timeStamp": "2019-03-16T04:02:23.051800Z",
        "ueIpv4Addr": "10.145.167.113",
        "startTime": "2019-03-16T04:02:20.002900Z",
        "userDataUsageMeasurements": [
          {
            "volumeMeasurement": {
              "totalVolume": 69991,
              "ulVolume": 15877,
              "dlVolume": 54114,
              "totalNbOfPackets": 139,
              "ulNbOfPackets": 69,
              "dlNbOfPackets": 70
            },
            "throughputMeasurement": {
              "ulThroughput": "41660 bps",
              "dlThroughput": "141990 bps",
              "ulPacketThroughput": "22.63 pps",
              "dlPacketThroughput": "22.96 pps"
            }
          }
        ]
      }
    ],
    "correlationId": "corr-53a02a33e37f",
    "appLabel": "instagram_IgSearchBrowse",
    "duration": 3.049
  },
  {
    "notificationItems": [
      {
        "eventType": "USER_DATA_USAGE_MEASURES",
        "timeStamp": "2019-03-16T04:02:27.388500Z",
        "ueIpv4Addr": "10.145.167.113",
        "startTime": "2019-03-16T04:02:25.023300Z",
        "userDataUsageMeasurements": [
          {
            "volumeMeasurement": {
              "totalVolume": 28505,
              "ulVolume": 2829,
              "dlVolume": 25676,
              "totalNbOfPackets": 52,
              "ulNbOfPackets": 26,
              "dlNbOfPackets": 26
            },
            "throughputMeasurement": {
              "ulThroughput": "9569 bps",
              "dlThroughput": "86846 bps",
              "ulPacketThroughput": "10.99 pps",
              "dlPacketThroughput": "10.99 pps"
            }
          }
        ]
      }
    ],
    "correlationId": "corr-4f3b78d71f0e",
    "appLabel": "instagram_IgSearchBrowse",
    "duration": 2.365
  },
  {
    "notificationItems": [
      {
        "eventType": "USER_DATA_USAGE_MEASURES",
        "timeStamp": "2019-03-16T04:02:34.846000Z",
        "ueIpv4Addr": "10.145.167.113",
        "startTime": "2019-03-16T04:02:32.370400Z",
        "userDataUsageMeasurements": [
          {
            "volumeMeasurement": {
              "totalVolume": 71648,
              "ulVolume": 21966,
              "dlVolume": 49682,
              "totalNbOfPackets": 132,
              "ulNbOfPackets": 67,
              "dlNbOfPackets": 65
            },
            "throughputMeasurement": {
              "ulThroughput": "70984 bps",
              "dlThroughput": "160549 bps",
              "ulPacketThroughput": "27.06 pps",
              "dlPacketThroughput": "26.26 pps"
            }
          }
        ]
      }
    ],
    "correlationId": "corr-9887b88fb57c",
    "appLabel": "instagram_IgSearchBrowse",
    "duration": 2.476
  },
  {
    "notificationItems": [
      {
        "eventType": "USER_DATA_USAGE_MEASURES",
        "timeStamp": "2019-03-16T04:02:36.062900Z",
        "ueIpv4Addr": "10.145.167.113",
        "startTime": "2019-03-16T04:02:35.941300Z",
        "userDataUsageMeasurements": [
          {
            "volumeMeasurement": {
              "totalVolume": 1006,
              "ulVolume": 326,
              "dlVolume": 680,
              "totalNbOfPackets": 5,
              "ulNbOfPackets": 3,
              "dlNbOfPackets": 2
            },
            "throughputMeasurement": {
              "ulThroughput": "21447 bps",
              "dlThroughput": "44737 bps",
              "ulPacketThroughput": "24.67 pps",
              "dlPacketThroughput": "16.45 pps"
            }
          }
        ]
      }
    ],
    "correlationId": "corr-f2b6371794ef",
    "appLabel": "instagram_IgSearchBrowse",
    "duration": 0.122
  },
  {
    "notificationItems": [
      {
        "eventType": "USER_DATA_USAGE_MEASURES",
        "timeStamp": "2019-03-16T04:02:44.627600Z",
        "ueIpv4Addr": "10.145.167.113",
        "startTime": "2019-03-16T04:02:41.923200Z",
        "userDataUsageMeasurements": [
          {
            "volumeMeasurement": {
              "totalVolume": 18859,
              "ulVolume": 2003,
              "dlVolume": 16856,
              "totalNbOfPackets": 37,
              "ulNbOfPackets": 20,
              "dlNbOfPackets": 17
            },
            "throughputMeasurement": {
              "ulThroughput": "5925 bps",
              "dlThroughput": "49862 bps",
              "ulPacketThroughput": "7.40 pps",
              "dlPacketThroughput": "6.29 pps"
            }
          }
        ]
      }
    ],
    "correlationId": "corr-be5e9e63ba43",
    "appLabel": "instagram_IgSearchBrowse",
    "duration": 2.704
  },
  {
    "notificationItems": [
      {
        "eventType": "USER_DATA_USAGE_MEASURES",
        "timeStamp": "2019-03-16T04:02:47.871700Z",
        "ueIpv4Addr": "10.145.167.113",
        "startTime": "2019-03-16T04:02:47.848800Z",
        "userDataUsageMeasurements": [
          {
            "volumeMeasurement": {
              "totalVolume": 147,
              "ulVolume": 91,
              "dlVolume": 56,
              "totalNbOfPackets": 2,
              "ulNbOfPackets": 1,
              "dlNbOfPackets": 1
            },
            "throughputMeasurement": {
              "ulThroughput": "31790 bps",
              "dlThroughput": "19563 bps",
              "ulPacketThroughput": "43.67 pps",
              "dlPacketThroughput": "43.67 pps"
            }
          }
        ]
      }
    ],
    "correlationId": "corr-a883c4928752",
    "appLabel": "instagram_IgSearchBrowse",
    "duration": 0.023
  },
  {
    "notificationItems": [
      {
        "eventType": "USER_DATA_USAGE_MEASURES",
        "timeStamp": "2019-03-16T04:02:53.350900Z",
        "ueIpv4Addr": "10.145.167.113",
        "startTime": "2019-03-16T04:02:50.501100Z",
        "userDataUsageMeasurements": [
          {
            "volumeMeasurement": {
              "totalVolume": 24232,
              "ulVolume": 2546,
              "dlVolume": 21686,
              "totalNbOfPackets": 49,
              "ulNbOfPackets": 26,
              "dlNbOfPackets": 23
            },
            "throughputMeasurement": {
              "ulThroughput": "7147 bps",
              "dlThroughput": "60877 bps",
              "ulPacketThroughput": "9.12 pps",
              "dlPacketThroughput": "8.07 pps"
            }
          }
        ]
      }
    ],
    "correlationId": "corr-eab9f7bf2632",
    "appLabel": "instagram_IgSearchBrowse",
    "duration": 2.85
  },
  {
    "notificationItems": [
      {
        "eventType": "USER_DATA_USAGE_MEASURES",
        "timeStamp": "2019-03-16T04:02:59.873700Z",
        "ueIpv4Addr": "10.145.167.113",
        "startTime": "2019-03-16T04:02:59.207000Z",
        "userDataUsageMeasurements": [
          {
            "volumeMeasurement": {
              "totalVolume": 44095,
              "ulVolume": 3279,
              "dlVolume": 40816,
              "totalNbOfPackets": 68,
              "ulNbOfPackets": 31,
              "dlNbOfPackets": 37
            },
            "throughputMeasurement": {
              "ulThroughput": "39346 bps",
              "dlThroughput": "489768 bps",
              "ulPacketThroughput": "46.50 pps",
              "dlPacketThroughput": "55.50 pps"
            }
          }
        ]
      }
    ],
    "correlationId": "corr-61e8355bdd85",
    "appLabel": "instagram_IgSearchBrowse",
    "duration": 0.667
  },
  {
    "notificationItems": [
      {
        "eventType": "USER_DATA_USAGE_MEASURES",
        "timeStamp": "2019-03-16T04:03:04.141400Z",
        "ueIpv4Addr": "10.145.167.113",
        "startTime": "2019-03-16T04:03:00.563200Z",
        "userDataUsageMeasurements": [
          {
            "volumeMeasurement": {
              "totalVolume": 237148,
              "ulVolume": 220067,
              "dlVolume": 17081,
              "totalNbOfPackets": 307,
              "ulNbOfPackets": 203,
              "dlNbOfPackets": 104
            },
            "throughputMeasurement": {
              "ulThroughput": "492017 bps",
              "dlThroughput": "38189 bps",
              "ulPacketThroughput": "56.73 pps",
              "dlPacketThroughput": "29.06 pps"
            }
          }
        ]
      }
    ],
    "correlationId": "corr-e6f42adcb9ee",
    "appLabel": "instagram_IgSearchBrowse",
    "duration": 3.578
  }
]